MANIFEST.in
README.rst
setup.py
collective/__init__.py
collective.js.jqsmartTruncation.egg-info/PKG-INFO
collective.js.jqsmartTruncation.egg-info/SOURCES.txt
collective.js.jqsmartTruncation.egg-info/dependency_links.txt
collective.js.jqsmartTruncation.egg-info/entry_points.txt
collective.js.jqsmartTruncation.egg-info/namespace_packages.txt
collective.js.jqsmartTruncation.egg-info/not-zip-safe
collective.js.jqsmartTruncation.egg-info/requires.txt
collective.js.jqsmartTruncation.egg-info/top_level.txt
collective/js/__init__.py
collective/js/jqsmartTruncation/__init__.py
collective/js/jqsmartTruncation/configure.zcml
collective/js/jqsmartTruncation/jquery.smartTruncation.js
collective/js/jqsmartTruncation/profiles/default/jsregistry.xml
collective/js/jqsmartTruncation/profiles/default/metadata.xml
docs/HISTORY.txt
docs/LICENSE.GPL
docs/LICENSE.txt