Metadata-Version: 1.0
Name: collective.js.jqsmartTruncation
Version: 1.0
Summary: This Package provides smart truncation.
Home-page: https://github.com/collective/collective.js.jqsmartTruncation
Author: Elio Schmutz
Author-email: mailto:info@4teamwork.ch
License: GPL2
Keywords: jquery smartTruncation
Platform: UNKNOWN
Classifier: Programming Language :: Python
Classifier: Topic :: Software Development :: Libraries :: Python Modules
